rocket.term-0.3.1.post1.data/scripts/rocketterm
rocketterm/__init__.py
rocketterm/comm.py
rocketterm/config.py
rocketterm/controller.py
rocketterm/emojis.py
rocketterm/hookmanager.py
rocketterm/logmanager.py
rocketterm/main.py
rocketterm/parser.py
rocketterm/realtime.py
rocketterm/rest.py
rocketterm/screen.py
rocketterm/terminal.py
rocketterm/types.py
rocketterm/utils.py
rocketterm/widgets.py
rocketterm/etc/rocket-term.ini
rocket.term-0.3.1.post1.dist-info/LICENSE
rocket.term-0.3.1.post1.dist-info/METADATA
rocket.term-0.3.1.post1.dist-info/WHEEL
rocket.term-0.3.1.post1.dist-info/top_level.txt
rocket.term-0.3.1.post1.dist-info/RECORD
